{
 "aggregate_function_based_on": "",
 "creation": "2025-02-02 19:41:41.108569",
 "docstatus": 0,
 "doctype": "Number Card",
 "document_type": "Burn Admission Assessment",
 "dynamic_filters_json": "[]",
 "filters_json": "[[\"Burn Admission Assessment\",\"sex\",\"=\",\"Male\",false]]",
 "function": "Count",
 "idx": 24,
 "is_public": 1,
 "is_standard": 1,
 "label": "Male Patients",
 "modified": "2025-02-03 14:41:05.814412",
 "modified_by": "Administrator",
 "module": "pills",
 "name": "No Of Male Patients",
 "owner": "Administrator",
 "parent_document_type": "",
 "report_function": "Sum",
 "show_percentage_stats": 0,
 "stats_time_interval": "Daily",
 "type": "Document Type"
}